chi/__init__.py
chi/__main__.py
chi/chi_main.py
chi/chi_to_py_final.py
chi/cli.py
chi/examples.py
chi/interpreter.py
chi/keywords.py
chi/lexer.py
chi/package_wrapper.py
chi/parser.py
chi/py_to_chi.py
chi/runner.py
chi/translator.py
chi/docs/CHICHEWA_LIST_METHODS.md
chi/docs/CHI_LANGUAGE_FEATURES.md
chi/docs/COMPLETE_FEATURES_OVERVIEW.txt
chi/docs/README.md
chi/docs/TRY_EXCEPT_FINALLY.md
chi_lang-1.0.0.dist-info/licenses/LICENSE
examples/README_EXAMPLES.md
examples/__init__.py
examples/chi_files/README.md
examples/chi_files/basic.chi
examples/chi_files/basic_if_test.chi
examples/chi_files/boolean_context_test.chi
examples/chi_files/boolean_test.chi
examples/chi_files/builtin_functions_demo.chi
examples/chi_files/business.chi
examples/chi_files/calculator.chi
examples/chi_files/chi_future_features.md
examples/chi_files/chi_language_introduction.chi
examples/chi_files/chichewa_exceptions_test.chi
examples/chi_files/chichewa_operators_test.chi
examples/chi_files/chita_boolean_test.chi
examples/chi_files/chita_clean_test.chi
examples/chi_files/chita_test.chi
examples/chi_files/complete_chi_demo.chi
examples/chi_files/complete_chichewa_test.chi
examples/chi_files/complete_dict_test.chi
examples/chi_files/complete_kaundula_demo.chi
examples/chi_files/complete_math_statistical_reference.chi
examples/chi_files/complete_mathematics_test.chi
examples/chi_files/comprehensive_test.chi
examples/chi_files/control_structures_demo.chi
examples/chi_files/data_types_demo.chi
examples/chi_files/debug.chi
examples/chi_files/debug_factorial.chi
examples/chi_files/dict_basic_test.chi
examples/chi_files/dict_literal_test.chi
examples/chi_files/dictionary_operations_demo.chi
examples/chi_files/edge_cases_test.chi
examples/chi_files/example.chi
examples/chi_files/example222.chi
examples/chi_files/example22_final_clean.chi
examples/chi_files/example22_to_chi.chi
examples/chi_files/exception_handling_demo.chi
examples/chi_files/factorial.chi
examples/chi_files/file_operations_demo.chi
examples/chi_files/file_operations_test.chi
chi_lang-1.0.0.dist-info/METADATA
chi_lang-1.0.0.dist-info/WHEEL
chi_lang-1.0.0.dist-info/entry_points.txt
chi_lang-1.0.0.dist-info/top_level.txt
chi_lang-1.0.0.dist-info/RECORD
