Metadata-Version: 2.4
Name: chi-lang
Version: 1.0.0
Summary: Chi Programming Language - A Chichewa-inspired programming language with intuitive syntax
Author-email: Duncan Masiye <duncanmasiye16@gmail.com>
Maintainer-email: Duncan Masiye <duncanmasiye16@gmail.com>
License: MIT License
Project-URL: Homepage, https://github.com/chi-lang/chi
Project-URL: Documentation, https://chi-lang.readthedocs.io
Project-URL: Repository, https://github.com/chi-lang/chi.git
Project-URL: Bug Tracker, https://github.com/chi-lang/chi/issues
Keywords: programming-language,chichewa,interpreter,compiler,translator
Classifier: Development Status :: 4 - Beta
Classifier: Intended Audience :: Developers
Classifier: License :: OSI Approved :: MIT License
Classifier: Operating System :: OS Independent
Classifier: Programming Language :: Python :: 3
Classifier: Programming Language :: Python :: 3.8
Classifier: Programming Language :: Python :: 3.9
Classifier: Programming Language :: Python :: 3.10
Classifier: Programming Language :: Python :: 3.11
Classifier: Programming Language :: Python :: 3.12
Classifier: Programming Language :: Python :: 3.13
Classifier: Topic :: Software Development :: Compilers
Classifier: Topic :: Software Development :: Interpreters
Classifier: Topic :: Software Development :: Libraries :: Python Modules
Requires-Python: >=3.8
License-File: LICENSE
Provides-Extra: dev
Requires-Dist: pytest>=7.0; extra == "dev"
Requires-Dist: black>=22.0; extra == "dev"
Requires-Dist: flake8>=4.0; extra == "dev"
Requires-Dist: mypy>=0.950; extra == "dev"
Provides-Extra: web
Requires-Dist: flask>=2.3.0; extra == "web"
Requires-Dist: flask-socketio>=5.3.0; extra == "web"
Requires-Dist: flask-cors>=4.0.0; extra == "web"
Dynamic: license-file
